<root>
    <item name='org.jboss.netty.handler.codec.http.HttpMethod org.jboss.netty.handler.codec.http.HttpMethod valueOf(java.lang.String)'>
        <annotation name='org.jetbrains.annotations.NotNull'/>
    </item>
    <item name='org.jboss.netty.handler.codec.http.DefaultHttpMessage DefaultHttpMessage(org.jboss.netty.handler.codec.http.HttpVersion) 0'>
        <annotation name='org.jetbrains.annotations.NotNull'/>
    </item>
    <item name='org.jboss.netty.handler.codec.http.HttpContentCompressor java.lang.String getTargetContentEncoding(java.lang.String) 0'>
        <annotation name='org.jetbrains.annotations.NotNull'/>
    </item>
    <item name='org.jboss.netty.handler.codec.http.QueryStringDecoder QueryStringDecoder(java.lang.String, java.nio.charset.Charset, boolean) 0'>
        <annotation name='org.jetbrains.annotations.NotNull'/>
    </item>
    <item name='org.jboss.netty.handler.codec.http.DefaultHttpRequest DefaultHttpRequest(org.jboss.netty.handler.codec.http.HttpVersion, org.jboss.netty.handler.codec.http.HttpMethod, java.lang.String) 0'>
        <annotation name='org.jetbrains.annotations.NotNull'/>
    </item>
    <item name='org.jboss.netty.handler.codec.http.HttpRequest void setMethod(org.jboss.netty.handler.codec.http.HttpMethod) 0'>
        <annotation name='org.jetbrains.annotations.NotNull'/>
        <annotation name='org.jetbrains.kannotator.runtime.annotations.Propagated'>
            <val name="value" val="{org.jetbrains.kannotator.controlFlow.builder.analysis.NullabilityKey.class}"/>
        </annotation>
    </item>
    <item name='org.jboss.netty.handler.codec.http.DefaultHttpMessage void setContent(org.jboss.netty.buffer.ChannelBuffer) 0'>
        <annotation name='org.jetbrains.annotations.NotNull'/>
        <annotation name='org.jetbrains.kannotator.runtime.annotations.Propagated'>
            <val name="value" val="{org.jetbrains.kannotator.controlFlow.builder.analysis.NullabilityKey.class}"/>
        </annotation>
    </item>
    <item name='org.jboss.netty.handler.codec.http.DefaultHttpRequest void setMethod(org.jboss.netty.handler.codec.http.HttpMethod) 0'>
        <annotation name='org.jetbrains.annotations.NotNull'/>
    </item>
    <item name='org.jboss.netty.handler.codec.http.DefaultHttpChunkTrailer java.util.List&lt;java.lang.String&gt; getHeaders(java.lang.String)'>
        <annotation name='org.jetbrains.annotations.NotNull'/>
    </item>
    <item name='org.jboss.netty.handler.codec.http.HttpChunkAggregator void messageReceived(org.jboss.netty.channel.ChannelHandlerContext, org.jboss.netty.channel.MessageEvent) 0'>
        <annotation name='org.jetbrains.annotations.NotNull'/>
        <annotation name='org.jetbrains.kannotator.runtime.annotations.Propagated'>
            <val name="value" val="{org.jetbrains.kannotator.controlFlow.builder.analysis.NullabilityKey.class}"/>
        </annotation>
    </item>
    <item name='org.jboss.netty.handler.codec.http.HttpHeaders boolean isKeepAlive(org.jboss.netty.handler.codec.http.HttpMessage) 0'>
        <annotation name='org.jetbrains.annotations.NotNull'/>
    </item>
    <item name='org.jboss.netty.handler.codec.http.QueryStringEncoder void addParam(java.lang.String, java.lang.String) 0'>
        <annotation name='org.jetbrains.annotations.NotNull'/>
    </item>
    <item name='org.jboss.netty.handler.codec.http.HttpMessage void addHeader(java.lang.String, java.lang.Object) 0'>
        <annotation name='org.jetbrains.annotations.NotNull'/>
        <annotation name='org.jetbrains.kannotator.runtime.annotations.Propagated'>
            <val name="value" val="{org.jetbrains.kannotator.controlFlow.builder.analysis.NullabilityKey.class}"/>
        </annotation>
    </item>
    <item name='org.jboss.netty.handler.codec.http.DefaultHttpChunkTrailer java.util.Set&lt;java.lang.String&gt; getHeaderNames()'>
        <annotation name='org.jetbrains.annotations.NotNull'/>
    </item>
    <item name='org.jboss.netty.handler.codec.http.DefaultHttpChunkTrailer void setHeader(java.lang.String, java.lang.Iterable&lt;?&gt;) 0'>
        <annotation name='org.jetbrains.annotations.NotNull'/>
    </item>
    <item name='org.jboss.netty.handler.codec.http.HttpContentEncoder void writeRequested(org.jboss.netty.channel.ChannelHandlerContext, org.jboss.netty.channel.MessageEvent) 1'>
        <annotation name='org.jetbrains.annotations.NotNull'/>
    </item>
    <item name='org.jboss.netty.handler.codec.http.HttpHeaders java.lang.String getHost(org.jboss.netty.handler.codec.http.HttpMessage, java.lang.String) 0'>
        <annotation name='org.jetbrains.annotations.NotNull'/>
    </item>
    <item name='org.jboss.netty.handler.codec.http.HttpMethod int compareTo(java.lang.Object) 0'>
        <annotation name='org.jetbrains.annotations.NotNull'/>
    </item>
    <item name='org.jboss.netty.handler.codec.http.HttpHeaders void set100ContinueExpected(org.jboss.netty.handler.codec.http.HttpMessage) 0'>
        <annotation name='org.jetbrains.annotations.NotNull'/>
    </item>
    <item name='org.jboss.netty.handler.codec.http.DefaultHttpMessage java.util.List&lt;java.lang.String&gt; getHeaders(java.lang.String) 0'>
        <annotation name='org.jetbrains.annotations.NotNull'/>
    </item>
    <item name='org.jboss.netty.handler.codec.http.HttpChunkTrailer void removeHeader(java.lang.String) 0'>
        <annotation name='org.jetbrains.annotations.NotNull'/>
        <annotation name='org.jetbrains.kannotator.runtime.annotations.Propagated'>
            <val name="value" val="{org.jetbrains.kannotator.controlFlow.builder.analysis.NullabilityKey.class}"/>
        </annotation>
    </item>
    <item name='org.jboss.netty.handler.codec.http.DefaultHttpMessage java.util.List&lt;java.lang.String&gt; getHeaders(java.lang.String)'>
        <annotation name='org.jetbrains.annotations.NotNull'/>
    </item>
    <item name='org.jboss.netty.handler.codec.http.QueryStringDecoder QueryStringDecoder(java.lang.String, java.nio.charset.Charset, boolean) 1'>
        <annotation name='org.jetbrains.annotations.NotNull'/>
    </item>
    <item name='org.jboss.netty.handler.codec.http.HttpResponseDecoder org.jboss.netty.handler.codec.http.HttpMessage createMessage(java.lang.String[])'>
        <annotation name='org.jetbrains.annotations.NotNull'/>
    </item>
    <item name='org.jboss.netty.handler.codec.http.DefaultHttpRequest DefaultHttpRequest(org.jboss.netty.handler.codec.http.HttpVersion, org.jboss.netty.handler.codec.http.HttpMethod, java.lang.String) 1'>
        <annotation name='org.jetbrains.annotations.NotNull'/>
    </item>
    <item name='org.jboss.netty.handler.codec.http.HttpContentEncoder void beforeRemove(org.jboss.netty.channel.ChannelHandlerContext) 0'>
        <annotation name='org.jetbrains.annotations.NotNull'/>
        <annotation name='org.jetbrains.kannotator.runtime.annotations.Propagated'>
            <val name="value" val="{org.jetbrains.kannotator.controlFlow.builder.analysis.NullabilityKey.class}"/>
        </annotation>
    </item>
    <item name='org.jboss.netty.handler.codec.http.HttpMessage java.util.List&lt;java.lang.String&gt; getHeaders(java.lang.String) 0'>
        <annotation name='org.jetbrains.annotations.NotNull'/>
        <annotation name='org.jetbrains.kannotator.runtime.annotations.Propagated'>
            <val name="value" val="{org.jetbrains.kannotator.controlFlow.builder.analysis.NullabilityKey.class}"/>
        </annotation>
    </item>
    <item name='org.jboss.netty.handler.codec.http.HttpRequestEncoder void encodeInitialLine(org.jboss.netty.buffer.ChannelBuffer, org.jboss.netty.handler.codec.http.HttpMessage) 0'>
        <annotation name='org.jetbrains.annotations.NotNull'/>
    </item>
    <item name='org.jboss.netty.handler.codec.http.DefaultHttpMessage void setHeader(java.lang.String, java.lang.Iterable&lt;?&gt;) 1'>
        <annotation name='org.jetbrains.annotations.NotNull'/>
    </item>
    <item name='org.jboss.netty.handler.codec.http.HttpRequestDecoder org.jboss.netty.handler.codec.http.HttpMessage createMessage(java.lang.String[])'>
        <annotation name='org.jetbrains.annotations.NotNull'/>
    </item>
    <item name='org.jboss.netty.handler.codec.http.HttpContentDecoder void messageReceived(org.jboss.netty.channel.ChannelHandlerContext, org.jboss.netty.channel.MessageEvent) 0'>
        <annotation name='org.jetbrains.annotations.NotNull'/>
        <annotation name='org.jetbrains.kannotator.runtime.annotations.Propagated'>
            <val name="value" val="{org.jetbrains.kannotator.controlFlow.builder.analysis.NullabilityKey.class}"/>
        </annotation>
    </item>
    <item name='org.jboss.netty.handler.codec.http.HttpMessageEncoder void encodeInitialLine(org.jboss.netty.buffer.ChannelBuffer, org.jboss.netty.handler.codec.http.HttpMessage) 0'>
        <annotation name='org.jetbrains.annotations.NotNull'/>
        <annotation name='org.jetbrains.kannotator.runtime.annotations.Propagated'>
            <val name="value" val="{org.jetbrains.kannotator.controlFlow.builder.analysis.NullabilityKey.class}"/>
        </annotation>
    </item>
    <item name='org.jboss.netty.handler.codec.http.HttpMessage void setHeader(java.lang.String, java.lang.Object) 0'>
        <annotation name='org.jetbrains.annotations.NotNull'/>
        <annotation name='org.jetbrains.kannotator.runtime.annotations.Propagated'>
            <val name="value" val="{org.jetbrains.kannotator.controlFlow.builder.analysis.NullabilityKey.class}"/>
        </annotation>
    </item>
    <item name='org.jboss.netty.handler.codec.http.QueryStringEncoder void addParam(java.lang.String, java.lang.String) 1'>
        <annotation name='org.jetbrains.annotations.NotNull'/>
    </item>
    <item name='org.jboss.netty.handler.codec.http.DefaultCookie void setPorts(java.lang.Iterable&lt;java.lang.Integer&gt;) 0'>
        <annotation name='org.jetbrains.annotations.NotNull'/>
    </item>
    <item name='org.jboss.netty.handler.codec.http.QueryStringDecoder java.lang.String decodeComponent(java.lang.String)'>
        <annotation name='org.jetbrains.annotations.NotNull'/>
    </item>
    <item name='org.jboss.netty.handler.codec.http.HttpChunkTrailer void setHeader(java.lang.String, java.lang.Object) 0'>
        <annotation name='org.jetbrains.annotations.NotNull'/>
        <annotation name='org.jetbrains.kannotator.runtime.annotations.Propagated'>
            <val name="value" val="{org.jetbrains.kannotator.controlFlow.builder.analysis.NullabilityKey.class}"/>
        </annotation>
    </item>
    <item name='org.jboss.netty.handler.codec.http.HttpServerCodec void handleDownstream(org.jboss.netty.channel.ChannelHandlerContext, org.jboss.netty.channel.ChannelEvent) 0'>
        <annotation name='org.jetbrains.annotations.NotNull'/>
        <annotation name='org.jetbrains.kannotator.runtime.annotations.Propagated'>
            <val name="value" val="{org.jetbrains.kannotator.controlFlow.builder.analysis.NullabilityKey.class}"/>
        </annotation>
    </item>
    <item name='org.jboss.netty.handler.codec.http.QueryStringDecoder QueryStringDecoder(java.net.URI, java.lang.String) 0'>
        <annotation name='org.jetbrains.annotations.NotNull'/>
    </item>
    <item name='org.jboss.netty.handler.codec.http.HttpMethod int compareTo(org.jboss.netty.handler.codec.http.HttpMethod) 0'>
        <annotation name='org.jetbrains.annotations.NotNull'/>
    </item>
    <item name='org.jboss.netty.handler.codec.http.HttpContentDecoder void beforeRemove(org.jboss.netty.channel.ChannelHandlerContext) 0'>
        <annotation name='org.jetbrains.annotations.NotNull'/>
        <annotation name='org.jetbrains.kannotator.runtime.annotations.Propagated'>
            <val name="value" val="{org.jetbrains.kannotator.controlFlow.builder.analysis.NullabilityKey.class}"/>
        </annotation>
    </item>
    <item name='org.jboss.netty.handler.codec.http.HttpMessage java.lang.String getHeader(java.lang.String) 0'>
        <annotation name='org.jetbrains.annotations.NotNull'/>
        <annotation name='org.jetbrains.kannotator.runtime.annotations.Propagated'>
            <val name="value" val="{org.jetbrains.kannotator.controlFlow.builder.analysis.NullabilityKey.class}"/>
        </annotation>
    </item>
    <item name='org.jboss.netty.handler.codec.http.HttpMessageDecoder java.lang.Object decode(org.jboss.netty.channel.ChannelHandlerContext, org.jboss.netty.channel.Channel, org.jboss.netty.buffer.ChannelBuffer, java.lang.Enum) 2'>
        <annotation name='org.jetbrains.annotations.NotNull'/>
        <annotation name='org.jetbrains.kannotator.runtime.annotations.Propagated'>
            <val name="value" val="{org.jetbrains.kannotator.controlFlow.builder.analysis.NullabilityKey.class}"/>
        </annotation>
    </item>
    <item name='org.jboss.netty.handler.codec.http.DefaultHttpMessage void addHeader(java.lang.String, java.lang.Object) 0'>
        <annotation name='org.jetbrains.annotations.NotNull'/>
    </item>
    <item name='org.jboss.netty.handler.codec.http.HttpResponse void setStatus(org.jboss.netty.handler.codec.http.HttpResponseStatus) 0'>
        <annotation name='org.jetbrains.annotations.NotNull'/>
        <annotation name='org.jetbrains.kannotator.runtime.annotations.Propagated'>
            <val name="value" val="{org.jetbrains.kannotator.controlFlow.builder.analysis.NullabilityKey.class}"/>
        </annotation>
    </item>
    <item name='org.jboss.netty.handler.codec.http.DefaultCookie void setPorts(int...) 0'>
        <annotation name='org.jetbrains.annotations.NotNull'/>
    </item>
    <item name='org.jboss.netty.handler.codec.http.HttpHeaders void addHeader(org.jboss.netty.handler.codec.http.HttpMessage, java.lang.String, java.lang.Object) 0'>
        <annotation name='org.jetbrains.annotations.NotNull'/>
    </item>
    <item name='org.jboss.netty.handler.codec.http.DefaultHttpChunk void setContent(org.jboss.netty.buffer.ChannelBuffer) 0'>
        <annotation name='org.jetbrains.annotations.NotNull'/>
    </item>
    <item name='org.jboss.netty.handler.codec.http.HttpHeaders java.lang.String getHeader(org.jboss.netty.handler.codec.http.HttpMessage, java.lang.String, java.lang.String) 0'>
        <annotation name='org.jetbrains.annotations.NotNull'/>
    </item>
    <item name='org.jboss.netty.handler.codec.http.HttpHeaders java.lang.String getHost(org.jboss.netty.handler.codec.http.HttpMessage) 0'>
        <annotation name='org.jetbrains.annotations.NotNull'/>
    </item>
    <item name='org.jboss.netty.handler.codec.http.DefaultHttpChunkTrailer void removeHeader(java.lang.String) 0'>
        <annotation name='org.jetbrains.annotations.NotNull'/>
    </item>
    <item name='org.jboss.netty.handler.codec.http.HttpContentEncoder org.jboss.netty.handler.codec.embedder.EncoderEmbedder&lt;org.jboss.netty.buffer.ChannelBuffer&gt; newContentEncoder(org.jboss.netty.handler.codec.http.HttpMessage, java.lang.String) 0'>
        <annotation name='org.jetbrains.annotations.NotNull'/>
        <annotation name='org.jetbrains.kannotator.runtime.annotations.Propagated'>
            <val name="value" val="{org.jetbrains.kannotator.controlFlow.builder.analysis.NullabilityKey.class}"/>
        </annotation>
    </item>
    <item name='org.jboss.netty.handler.codec.http.QueryStringDecoder QueryStringDecoder(java.lang.String, java.nio.charset.Charset) 0'>
        <annotation name='org.jetbrains.annotations.NotNull'/>
    </item>
    <item name='org.jboss.netty.handler.codec.http.HttpResponseStatus int compareTo(org.jboss.netty.handler.codec.http.HttpResponseStatus) 0'>
        <annotation name='org.jetbrains.annotations.NotNull'/>
    </item>
    <item name='org.jboss.netty.handler.codec.http.DefaultHttpRequest DefaultHttpRequest(org.jboss.netty.handler.codec.http.HttpVersion, org.jboss.netty.handler.codec.http.HttpMethod, java.lang.String) 2'>
        <annotation name='org.jetbrains.annotations.NotNull'/>
    </item>
    <item name='org.jboss.netty.handler.codec.http.HttpMessage void setContent(org.jboss.netty.buffer.ChannelBuffer) 0'>
        <annotation name='org.jetbrains.annotations.NotNull'/>
        <annotation name='org.jetbrains.kannotator.runtime.annotations.Propagated'>
            <val name="value" val="{org.jetbrains.kannotator.controlFlow.builder.analysis.NullabilityKey.class}"/>
        </annotation>
    </item>
    <item name='org.jboss.netty.handler.codec.http.DefaultHttpMessage void setProtocolVersion(org.jboss.netty.handler.codec.http.HttpVersion) 0'>
        <annotation name='org.jetbrains.annotations.NotNull'/>
    </item>
    <item name='org.jboss.netty.handler.codec.http.HttpContentDecoder void messageReceived(org.jboss.netty.channel.ChannelHandlerContext, org.jboss.netty.channel.MessageEvent) 1'>
        <annotation name='org.jetbrains.annotations.NotNull'/>
    </item>
    <item name='org.jboss.netty.handler.codec.http.DefaultHttpRequest void setUri(java.lang.String) 0'>
        <annotation name='org.jetbrains.annotations.NotNull'/>
    </item>
    <item name='org.jboss.netty.handler.codec.http.HttpChunkAggregator void beforeRemove(org.jboss.netty.channel.ChannelHandlerContext) 0'>
        <annotation name='org.jetbrains.annotations.NotNull'/>
        <annotation name='org.jetbrains.kannotator.runtime.annotations.Propagated'>
            <val name="value" val="{org.jetbrains.kannotator.controlFlow.builder.analysis.NullabilityKey.class}"/>
        </annotation>
    </item>
    <item name='org.jboss.netty.handler.codec.http.HttpResponseStatus java.lang.String getReasonPhrase()'>
        <annotation name='org.jetbrains.annotations.NotNull'/>
    </item>
    <item name='org.jboss.netty.handler.codec.http.DefaultHttpResponse DefaultHttpResponse(org.jboss.netty.handler.codec.http.HttpVersion, org.jboss.netty.handler.codec.http.HttpResponseStatus) 0'>
        <annotation name='org.jetbrains.annotations.NotNull'/>
    </item>
    <item name='org.jboss.netty.handler.codec.http.DefaultHttpChunkTrailer void setContent(org.jboss.netty.buffer.ChannelBuffer) 0'>
        <annotation name='org.jetbrains.annotations.NotNull'/>
        <annotation name='org.jetbrains.kannotator.runtime.annotations.Propagated'>
            <val name="value" val="{org.jetbrains.kannotator.controlFlow.builder.analysis.NullabilityKey.class}"/>
        </annotation>
    </item>
    <item name='org.jboss.netty.handler.codec.http.HttpResponseEncoder void encodeInitialLine(org.jboss.netty.buffer.ChannelBuffer, org.jboss.netty.handler.codec.http.HttpMessage) 1'>
        <annotation name='org.jetbrains.annotations.NotNull'/>
    </item>
    <item name='org.jboss.netty.handler.codec.http.DefaultHttpMessage void setHeader(java.lang.String, java.lang.Iterable&lt;?&gt;) 0'>
        <annotation name='org.jetbrains.annotations.NotNull'/>
    </item>
    <item name='org.jboss.netty.handler.codec.http.HttpContentEncoder void channelClosed(org.jboss.netty.channel.ChannelHandlerContext, org.jboss.netty.channel.ChannelStateEvent) 0'>
        <annotation name='org.jetbrains.annotations.NotNull'/>
    </item>
    <item name='org.jboss.netty.handler.codec.http.QueryStringDecoder QueryStringDecoder(java.net.URI) 0'>
        <annotation name='org.jetbrains.annotations.NotNull'/>
    </item>
    <item name='org.jboss.netty.handler.codec.http.QueryStringDecoder QueryStringDecoder(java.lang.String, java.nio.charset.Charset, boolean, int) 1'>
        <annotation name='org.jetbrains.annotations.NotNull'/>
    </item>
    <item name='org.jboss.netty.handler.codec.http.DefaultHttpMessage void removeHeader(java.lang.String) 0'>
        <annotation name='org.jetbrains.annotations.NotNull'/>
    </item>
    <item name='org.jboss.netty.handler.codec.http.DefaultHttpChunkTrailer java.lang.String getHeader(java.lang.String) 0'>
        <annotation name='org.jetbrains.annotations.NotNull'/>
    </item>
    <item name='org.jboss.netty.handler.codec.http.DefaultHttpMessage void setHeader(java.lang.String, java.lang.Object) 0'>
        <annotation name='org.jetbrains.annotations.NotNull'/>
    </item>
    <item name='org.jboss.netty.handler.codec.http.HttpMessageDecoder java.lang.Object decode(org.jboss.netty.channel.ChannelHandlerContext, org.jboss.netty.channel.Channel, org.jboss.netty.buffer.ChannelBuffer, java.lang.Enum) 3'>
        <annotation name='org.jetbrains.annotations.NotNull'/>
    </item>
    <item name='org.jboss.netty.handler.codec.http.HttpContentEncoder java.lang.String getTargetContentEncoding(java.lang.String) 0'>
        <annotation name='org.jetbrains.annotations.NotNull'/>
        <annotation name='org.jetbrains.kannotator.runtime.annotations.Propagated'>
            <val name="value" val="{org.jetbrains.kannotator.controlFlow.builder.analysis.NullabilityKey.class}"/>
        </annotation>
    </item>
    <item name='org.jboss.netty.handler.codec.http.DefaultHttpMessage java.lang.String getHeader(java.lang.String) 0'>
        <annotation name='org.jetbrains.annotations.NotNull'/>
    </item>
    <item name='org.jboss.netty.handler.codec.http.HttpVersion int compareTo(java.lang.Object) 0'>
        <annotation name='org.jetbrains.annotations.NotNull'/>
    </item>
    <item name='org.jboss.netty.handler.codec.http.HttpHeaders void setIntHeader(org.jboss.netty.handler.codec.http.HttpMessage, java.lang.String, java.lang.Iterable&lt;java.lang.Integer&gt;) 0'>
        <annotation name='org.jetbrains.annotations.NotNull'/>
    </item>
    <item name='org.jboss.netty.handler.codec.http.HttpMessageDecoder java.lang.Object decode(org.jboss.netty.channel.ChannelHandlerContext, org.jboss.netty.channel.Channel, org.jboss.netty.buffer.ChannelBuffer, org.jboss.netty.handler.codec.http.HttpMessageDecoder.State) 3'>
        <annotation name='org.jetbrains.annotations.NotNull'/>
    </item>
    <item name='org.jboss.netty.handler.codec.http.DefaultCookie DefaultCookie(java.lang.String, java.lang.String) 1'>
        <annotation name='org.jetbrains.annotations.NotNull'/>
    </item>
    <item name='org.jboss.netty.handler.codec.http.HttpChunk void setContent(org.jboss.netty.buffer.ChannelBuffer) 0'>
        <annotation name='org.jetbrains.annotations.NotNull'/>
        <annotation name='org.jetbrains.kannotator.runtime.annotations.Propagated'>
            <val name="value" val="{org.jetbrains.kannotator.controlFlow.builder.analysis.NullabilityKey.class}"/>
        </annotation>
    </item>
    <item name='org.jboss.netty.handler.codec.http.DefaultHttpResponse DefaultHttpResponse(org.jboss.netty.handler.codec.http.HttpVersion, org.jboss.netty.handler.codec.http.HttpResponseStatus) 1'>
        <annotation name='org.jetbrains.annotations.NotNull'/>
    </item>
    <item name='org.jboss.netty.handler.codec.http.CookieEncoder void addCookie(java.lang.String, java.lang.String) 1'>
        <annotation name='org.jetbrains.annotations.NotNull'/>
    </item>
    <item name='org.jboss.netty.handler.codec.http.HttpResponseEncoder void encodeInitialLine(org.jboss.netty.buffer.ChannelBuffer, org.jboss.netty.handler.codec.http.HttpMessage) 0'>
        <annotation name='org.jetbrains.annotations.NotNull'/>
    </item>
    <item name='org.jboss.netty.handler.codec.http.HttpContentEncoder void messageReceived(org.jboss.netty.channel.ChannelHandlerContext, org.jboss.netty.channel.MessageEvent) 1'>
        <annotation name='org.jetbrains.annotations.NotNull'/>
    </item>
    <item name='org.jboss.netty.handler.codec.http.HttpChunk org.jboss.netty.buffer.ChannelBuffer getContent()'>
        <annotation name='org.jetbrains.annotations.NotNull'/>
        <annotation name='org.jetbrains.kannotator.runtime.annotations.Propagated'>
            <val name="value" val="{org.jetbrains.kannotator.controlFlow.builder.analysis.NullabilityKey.class}"/>
        </annotation>
    </item>
    <item name='org.jboss.netty.handler.codec.http.QueryStringDecoder QueryStringDecoder(java.lang.String, java.nio.charset.Charset, boolean, int) 0'>
        <annotation name='org.jetbrains.annotations.NotNull'/>
    </item>
    <item name='org.jboss.netty.handler.codec.http.DefaultHttpChunkTrailer java.util.List&lt;java.lang.String&gt; getHeaders(java.lang.String) 0'>
        <annotation name='org.jetbrains.annotations.NotNull'/>
    </item>
    <item name='org.jboss.netty.handler.codec.http.HttpContentEncoder void beforeAdd(org.jboss.netty.channel.ChannelHandlerContext) 0'>
        <annotation name='org.jetbrains.annotations.NotNull'/>
        <annotation name='org.jetbrains.kannotator.runtime.annotations.Propagated'>
            <val name="value" val="{org.jetbrains.kannotator.controlFlow.builder.analysis.NullabilityKey.class}"/>
        </annotation>
    </item>
    <item name='org.jboss.netty.handler.codec.http.HttpContentEncoder void writeRequested(org.jboss.netty.channel.ChannelHandlerContext, org.jboss.netty.channel.MessageEvent) 0'>
        <annotation name='org.jetbrains.annotations.NotNull'/>
        <annotation name='org.jetbrains.kannotator.runtime.annotations.Propagated'>
            <val name="value" val="{org.jetbrains.kannotator.controlFlow.builder.analysis.NullabilityKey.class}"/>
        </annotation>
    </item>
    <item name='org.jboss.netty.handler.codec.http.DefaultHttpChunkTrailer void setHeader(java.lang.String, java.lang.Iterable&lt;?&gt;) 1'>
        <annotation name='org.jetbrains.annotations.NotNull'/>
    </item>
    <item name='org.jboss.netty.handler.codec.http.DefaultHttpChunk DefaultHttpChunk(org.jboss.netty.buffer.ChannelBuffer) 0'>
        <annotation name='org.jetbrains.annotations.NotNull'/>
    </item>
    <item name='org.jboss.netty.handler.codec.http.HttpChunkTrailer java.util.List&lt;java.util.Map.Entry&lt;java.lang.String,java.lang.String&gt;&gt; getHeaders()'>
        <annotation name='org.jetbrains.annotations.NotNull'/>
        <annotation name='org.jetbrains.kannotator.runtime.annotations.Propagated'>
            <val name="value" val="{org.jetbrains.kannotator.controlFlow.builder.analysis.NullabilityKey.class}"/>
        </annotation>
    </item>
    <item name='org.jboss.netty.handler.codec.http.HttpContentEncoder void messageReceived(org.jboss.netty.channel.ChannelHandlerContext, org.jboss.netty.channel.MessageEvent) 0'>
        <annotation name='org.jetbrains.annotations.NotNull'/>
    </item>
    <item name='org.jboss.netty.handler.codec.http.DefaultCookie int compareTo(org.jboss.netty.handler.codec.http.Cookie) 0'>
        <annotation name='org.jetbrains.annotations.NotNull'/>
    </item>
    <item name='org.jboss.netty.handler.codec.http.HttpServerCodec void handleUpstream(org.jboss.netty.channel.ChannelHandlerContext, org.jboss.netty.channel.ChannelEvent) 0'>
        <annotation name='org.jetbrains.annotations.NotNull'/>
        <annotation name='org.jetbrains.kannotator.runtime.annotations.Propagated'>
            <val name="value" val="{org.jetbrains.kannotator.controlFlow.builder.analysis.NullabilityKey.class}"/>
        </annotation>
    </item>
    <item name='org.jboss.netty.handler.codec.http.HttpMessage java.util.Set&lt;java.lang.String&gt; getHeaderNames()'>
        <annotation name='org.jetbrains.annotations.NotNull'/>
        <annotation name='org.jetbrains.kannotator.runtime.annotations.Propagated'>
            <val name="value" val="{org.jetbrains.kannotator.controlFlow.builder.analysis.NullabilityKey.class}"/>
        </annotation>
    </item>
    <item name='org.jboss.netty.handler.codec.http.HttpContentCompressor org.jboss.netty.handler.codec.embedder.EncoderEmbedder&lt;org.jboss.netty.buffer.ChannelBuffer&gt; newContentEncoder(org.jboss.netty.handler.codec.http.HttpMessage, java.lang.String) 0'>
        <annotation name='org.jetbrains.annotations.NotNull'/>
    </item>
    <item name='org.jboss.netty.handler.codec.http.HttpChunkTrailer java.util.List&lt;java.lang.String&gt; getHeaders(java.lang.String) 0'>
        <annotation name='org.jetbrains.annotations.NotNull'/>
        <annotation name='org.jetbrains.kannotator.runtime.annotations.Propagated'>
            <val name="value" val="{org.jetbrains.kannotator.controlFlow.builder.analysis.NullabilityKey.class}"/>
        </annotation>
    </item>
    <item name='org.jboss.netty.handler.codec.http.QueryStringEncoder QueryStringEncoder(java.lang.String, java.nio.charset.Charset) 0'>
        <annotation name='org.jetbrains.annotations.NotNull'/>
    </item>
    <item name='org.jboss.netty.handler.codec.http.HttpMessage void setHeader(java.lang.String, java.lang.Iterable&lt;?&gt;) 1'>
        <annotation name='org.jetbrains.annotations.NotNull'/>
        <annotation name='org.jetbrains.kannotator.runtime.annotations.Propagated'>
            <val name="value" val="{org.jetbrains.kannotator.controlFlow.builder.analysis.NullabilityKey.class}"/>
        </annotation>
    </item>
    <item name='org.jboss.netty.handler.codec.http.QueryStringEncoder java.net.URI toUri()'>
        <annotation name='org.jetbrains.annotations.NotNull'/>
    </item>
    <item name='org.jboss.netty.handler.codec.http.QueryStringDecoder QueryStringDecoder(java.net.URI, java.nio.charset.Charset, int) 1'>
        <annotation name='org.jetbrains.annotations.NotNull'/>
    </item>
    <item name='org.jboss.netty.handler.codec.http.HttpVersion int compareTo(org.jboss.netty.handler.codec.http.HttpVersion) 0'>
        <annotation name='org.jetbrains.annotations.NotNull'/>
    </item>
    <item name='org.jboss.netty.handler.codec.http.HttpHeaders void setKeepAlive(org.jboss.netty.handler.codec.http.HttpMessage, boolean) 0'>
        <annotation name='org.jetbrains.annotations.NotNull'/>
    </item>
    <item name='org.jboss.netty.handler.codec.http.HttpResponseStatus org.jboss.netty.handler.codec.http.HttpResponseStatus valueOf(int)'>
        <annotation name='org.jetbrains.annotations.NotNull'/>
    </item>
    <item name='org.jboss.netty.handler.codec.http.DefaultHttpChunkTrailer org.jboss.netty.buffer.ChannelBuffer getContent()'>
        <annotation name='org.jetbrains.annotations.NotNull'/>
    </item>
    <item name='org.jboss.netty.handler.codec.http.HttpResponseStatus HttpResponseStatus(int, java.lang.String) 1'>
        <annotation name='org.jetbrains.annotations.NotNull'/>
    </item>
    <item name='org.jboss.netty.handler.codec.http.HttpChunkTrailer void setHeader(java.lang.String, java.lang.Iterable&lt;?&gt;) 0'>
        <annotation name='org.jetbrains.annotations.NotNull'/>
        <annotation name='org.jetbrains.kannotator.runtime.annotations.Propagated'>
            <val name="value" val="{org.jetbrains.kannotator.controlFlow.builder.analysis.NullabilityKey.class}"/>
        </annotation>
    </item>
    <item name='org.jboss.netty.handler.codec.http.HttpChunkTrailer java.lang.String getHeader(java.lang.String) 0'>
        <annotation name='org.jetbrains.annotations.NotNull'/>
        <annotation name='org.jetbrains.kannotator.runtime.annotations.Propagated'>
            <val name="value" val="{org.jetbrains.kannotator.controlFlow.builder.analysis.NullabilityKey.class}"/>
        </annotation>
    </item>
    <item name='org.jboss.netty.handler.codec.http.QueryStringDecoder QueryStringDecoder(java.net.URI, java.nio.charset.Charset) 0'>
        <annotation name='org.jetbrains.annotations.NotNull'/>
    </item>
    <item name='org.jboss.netty.handler.codec.http.HttpHeaders void setHeader(org.jboss.netty.handler.codec.http.HttpMessage, java.lang.String, java.lang.Iterable&lt;?&gt;) 0'>
        <annotation name='org.jetbrains.annotations.NotNull'/>
    </item>
    <item name='org.jboss.netty.handler.codec.http.HttpRequestEncoder void encodeInitialLine(org.jboss.netty.buffer.ChannelBuffer, org.jboss.netty.handler.codec.http.HttpMessage) 1'>
        <annotation name='org.jetbrains.annotations.NotNull'/>
    </item>
    <item name='org.jboss.netty.handler.codec.http.DefaultHttpChunkTrailer java.util.List&lt;java.util.Map.Entry&lt;java.lang.String,java.lang.String&gt;&gt; getHeaders()'>
        <annotation name='org.jetbrains.annotations.NotNull'/>
    </item>
    <item name='org.jboss.netty.handler.codec.http.HttpClientCodec void handleDownstream(org.jboss.netty.channel.ChannelHandlerContext, org.jboss.netty.channel.ChannelEvent) 0'>
        <annotation name='org.jetbrains.annotations.NotNull'/>
        <annotation name='org.jetbrains.kannotator.runtime.annotations.Propagated'>
            <val name="value" val="{org.jetbrains.kannotator.controlFlow.builder.analysis.NullabilityKey.class}"/>
        </annotation>
    </item>
    <item name='org.jboss.netty.handler.codec.http.HttpChunkTrailer java.util.List&lt;java.lang.String&gt; getHeaders(java.lang.String)'>
        <annotation name='org.jetbrains.annotations.NotNull'/>
        <annotation name='org.jetbrains.kannotator.runtime.annotations.Propagated'>
            <val name="value" val="{org.jetbrains.kannotator.controlFlow.builder.analysis.NullabilityKey.class}"/>
        </annotation>
    </item>
    <item name='org.jboss.netty.handler.codec.http.HttpContentDecoder java.lang.String getTargetContentEncoding(java.lang.String)'>
        <annotation name='org.jetbrains.annotations.NotNull'/>
    </item>
    <item name='org.jboss.netty.handler.codec.http.Cookie void setValue(java.lang.String) 0'>
        <annotation name='org.jetbrains.annotations.NotNull'/>
        <annotation name='org.jetbrains.kannotator.runtime.annotations.Propagated'>
            <val name="value" val="{org.jetbrains.kannotator.controlFlow.builder.analysis.NullabilityKey.class}"/>
        </annotation>
    </item>
    <item name='org.jboss.netty.handler.codec.http.QueryStringDecoder QueryStringDecoder(java.lang.String, java.lang.String) 0'>
        <annotation name='org.jetbrains.annotations.NotNull'/>
    </item>
    <item name='org.jboss.netty.handler.codec.http.HttpContentDecoder void channelClosed(org.jboss.netty.channel.ChannelHandlerContext, org.jboss.netty.channel.ChannelStateEvent) 0'>
        <annotation name='org.jetbrains.annotations.NotNull'/>
    </item>
    <item name='org.jboss.netty.handler.codec.http.HttpMessageEncoder java.lang.Object encode(org.jboss.netty.channel.ChannelHandlerContext, org.jboss.netty.channel.Channel, java.lang.Object) 0'>
        <annotation name='org.jetbrains.annotations.NotNull'/>
        <annotation name='org.jetbrains.kannotator.runtime.annotations.Propagated'>
            <val name="value" val="{org.jetbrains.kannotator.controlFlow.builder.analysis.NullabilityKey.class}"/>
        </annotation>
    </item>
    <item name='org.jboss.netty.handler.codec.http.QueryStringEncoder QueryStringEncoder(java.lang.String, java.nio.charset.Charset) 1'>
        <annotation name='org.jetbrains.annotations.NotNull'/>
    </item>
    <item name='org.jboss.netty.handler.codec.http.HttpMessage void setHeader(java.lang.String, java.lang.Iterable&lt;?&gt;) 0'>
        <annotation name='org.jetbrains.annotations.NotNull'/>
        <annotation name='org.jetbrains.kannotator.runtime.annotations.Propagated'>
            <val name="value" val="{org.jetbrains.kannotator.controlFlow.builder.analysis.NullabilityKey.class}"/>
        </annotation>
    </item>
    <item name='org.jboss.netty.handler.codec.http.HttpHeaders long getContentLength(org.jboss.netty.handler.codec.http.HttpMessage, long) 0'>
        <annotation name='org.jetbrains.annotations.NotNull'/>
    </item>
    <item name='org.jboss.netty.handler.codec.http.HttpHeaders void setIntHeader(org.jboss.netty.handler.codec.http.HttpMessage, java.lang.String, int) 0'>
        <annotation name='org.jetbrains.annotations.NotNull'/>
    </item>
    <item name='org.jboss.netty.handler.codec.http.DefaultHttpMessage java.util.List&lt;java.util.Map.Entry&lt;java.lang.String,java.lang.String&gt;&gt; getHeaders()'>
        <annotation name='org.jetbrains.annotations.NotNull'/>
    </item>
    <item name='org.jboss.netty.handler.codec.http.QueryStringDecoder QueryStringDecoder(java.lang.String, java.nio.charset.Charset) 1'>
        <annotation name='org.jetbrains.annotations.NotNull'/>
    </item>
    <item name='org.jboss.netty.handler.codec.http.HttpMessage boolean containsHeader(java.lang.String) 0'>
        <annotation name='org.jetbrains.annotations.NotNull'/>
        <annotation name='org.jetbrains.kannotator.runtime.annotations.Propagated'>
            <val name="value" val="{org.jetbrains.kannotator.controlFlow.builder.analysis.NullabilityKey.class}"/>
        </annotation>
    </item>
    <item name='org.jboss.netty.handler.codec.http.QueryStringDecoder QueryStringDecoder(java.net.URI, java.nio.charset.Charset, int) 0'>
        <annotation name='org.jetbrains.annotations.NotNull'/>
    </item>
    <item name='org.jboss.netty.handler.codec.http.HttpChunkAggregator void beforeAdd(org.jboss.netty.channel.ChannelHandlerContext) 0'>
        <annotation name='org.jetbrains.annotations.NotNull'/>
        <annotation name='org.jetbrains.kannotator.runtime.annotations.Propagated'>
            <val name="value" val="{org.jetbrains.kannotator.controlFlow.builder.analysis.NullabilityKey.class}"/>
        </annotation>
    </item>
    <item name='org.jboss.netty.handler.codec.http.Cookie void setPorts(int...) 0'>
        <annotation name='org.jetbrains.annotations.NotNull'/>
        <annotation name='org.jetbrains.kannotator.runtime.annotations.Propagated'>
            <val name="value" val="{org.jetbrains.kannotator.controlFlow.builder.analysis.NullabilityKey.class}"/>
        </annotation>
    </item>
    <item name='org.jboss.netty.handler.codec.http.HttpChunkTrailer void setHeader(java.lang.String, java.lang.Iterable&lt;?&gt;) 1'>
        <annotation name='org.jetbrains.annotations.NotNull'/>
        <annotation name='org.jetbrains.kannotator.runtime.annotations.Propagated'>
            <val name="value" val="{org.jetbrains.kannotator.controlFlow.builder.analysis.NullabilityKey.class}"/>
        </annotation>
    </item>
    <item name='org.jboss.netty.handler.codec.http.QueryStringDecoder QueryStringDecoder(java.lang.String, boolean) 0'>
        <annotation name='org.jetbrains.annotations.NotNull'/>
    </item>
    <item name='org.jboss.netty.handler.codec.http.QueryStringDecoder QueryStringDecoder(java.lang.String) 0'>
        <annotation name='org.jetbrains.annotations.NotNull'/>
    </item>
    <item name='org.jboss.netty.handler.codec.http.HttpHeaders void setHost(org.jboss.netty.handler.codec.http.HttpMessage, java.lang.String) 0'>
        <annotation name='org.jetbrains.annotations.NotNull'/>
    </item>
    <item name='org.jboss.netty.handler.codec.http.QueryStringDecoder QueryStringDecoder(java.net.URI, java.nio.charset.Charset) 1'>
        <annotation name='org.jetbrains.annotations.NotNull'/>
    </item>
    <item name='org.jboss.netty.handler.codec.http.HttpVersion org.jboss.netty.handler.codec.http.HttpVersion valueOf(java.lang.String)'>
        <annotation name='org.jetbrains.annotations.NotNull'/>
    </item>
    <item name='org.jboss.netty.handler.codec.http.HttpHeaders void setContentLength(org.jboss.netty.handler.codec.http.HttpMessage, long) 0'>
        <annotation name='org.jetbrains.annotations.NotNull'/>
    </item>
    <item name='org.jboss.netty.handler.codec.http.HttpMessage java.util.List&lt;java.lang.String&gt; getHeaders(java.lang.String)'>
        <annotation name='org.jetbrains.annotations.NotNull'/>
        <annotation name='org.jetbrains.kannotator.runtime.annotations.Propagated'>
            <val name="value" val="{org.jetbrains.kannotator.controlFlow.builder.analysis.NullabilityKey.class}"/>
        </annotation>
    </item>
    <item name='org.jboss.netty.handler.codec.http.QueryStringDecoder java.lang.String decodeComponent(java.lang.String, java.nio.charset.Charset)'>
        <annotation name='org.jetbrains.annotations.NotNull'/>
    </item>
    <item name='org.jboss.netty.handler.codec.http.HttpMessageDecoder boolean isContentAlwaysEmpty(org.jboss.netty.handler.codec.http.HttpMessage) 0'>
        <annotation name='org.jetbrains.annotations.NotNull'/>
        <annotation name='org.jetbrains.kannotator.runtime.annotations.Propagated'>
            <val name="value" val="{org.jetbrains.kannotator.controlFlow.builder.analysis.NullabilityKey.class}"/>
        </annotation>
    </item>
    <item name='org.jboss.netty.handler.codec.http.HttpHeaders void setHeader(org.jboss.netty.handler.codec.http.HttpMessage, java.lang.String, java.lang.Object) 0'>
        <annotation name='org.jetbrains.annotations.NotNull'/>
    </item>
    <item name='org.jboss.netty.handler.codec.http.HttpChunkTrailer void addHeader(java.lang.String, java.lang.Object) 0'>
        <annotation name='org.jetbrains.annotations.NotNull'/>
        <annotation name='org.jetbrains.kannotator.runtime.annotations.Propagated'>
            <val name="value" val="{org.jetbrains.kannotator.controlFlow.builder.analysis.NullabilityKey.class}"/>
        </annotation>
    </item>
    <item name='org.jboss.netty.handler.codec.http.HttpRequest void setUri(java.lang.String) 0'>
        <annotation name='org.jetbrains.annotations.NotNull'/>
        <annotation name='org.jetbrains.kannotator.runtime.annotations.Propagated'>
            <val name="value" val="{org.jetbrains.kannotator.controlFlow.builder.analysis.NullabilityKey.class}"/>
        </annotation>
    </item>
    <item name='org.jboss.netty.handler.codec.http.HttpResponseDecoder org.jboss.netty.handler.codec.http.HttpMessage createMessage(java.lang.String[]) 0'>
        <annotation name='org.jetbrains.annotations.NotNull'/>
    </item>
    <item name='org.jboss.netty.handler.codec.http.CookieDecoder java.util.Set&lt;org.jboss.netty.handler.codec.http.Cookie&gt; decode(java.lang.String) 0'>
        <annotation name='org.jetbrains.annotations.NotNull'/>
    </item>
    <item name='org.jboss.netty.handler.codec.http.DefaultHttpMessage boolean containsHeader(java.lang.String) 0'>
        <annotation name='org.jetbrains.annotations.NotNull'/>
    </item>
    <item name='org.jboss.netty.handler.codec.http.DefaultCookie void setValue(java.lang.String) 0'>
        <annotation name='org.jetbrains.annotations.NotNull'/>
    </item>
    <item name='org.jboss.netty.handler.codec.http.DefaultHttpChunkTrailer boolean containsHeader(java.lang.String) 0'>
        <annotation name='org.jetbrains.annotations.NotNull'/>
    </item>
    <item name='org.jboss.netty.handler.codec.http.DefaultHttpChunkTrailer void setHeader(java.lang.String, java.lang.Object) 0'>
        <annotation name='org.jetbrains.annotations.NotNull'/>
    </item>
    <item name='org.jboss.netty.handler.codec.http.DefaultCookie java.lang.String getName()'>
        <annotation name='org.jetbrains.annotations.NotNull'/>
    </item>
    <item name='org.jboss.netty.handler.codec.http.DefaultHttpChunkTrailer void addHeader(java.lang.String, java.lang.Object) 0'>
        <annotation name='org.jetbrains.annotations.NotNull'/>
    </item>
    <item name='org.jboss.netty.handler.codec.http.HttpHeaders int getIntHeader(org.jboss.netty.handler.codec.http.HttpMessage, java.lang.String) 0'>
        <annotation name='org.jetbrains.annotations.NotNull'/>
    </item>
    <item name='org.jboss.netty.handler.codec.http.QueryStringEncoder QueryStringEncoder(java.lang.String, java.lang.String) 0'>
        <annotation name='org.jetbrains.annotations.NotNull'/>
    </item>
    <item name='org.jboss.netty.handler.codec.http.HttpMessageEncoder void encodeInitialLine(org.jboss.netty.buffer.ChannelBuffer, org.jboss.netty.handler.codec.http.HttpMessage) 1'>
        <annotation name='org.jetbrains.annotations.NotNull'/>
        <annotation name='org.jetbrains.kannotator.runtime.annotations.Propagated'>
            <val name="value" val="{org.jetbrains.kannotator.controlFlow.builder.analysis.NullabilityKey.class}"/>
        </annotation>
    </item>
    <item name='org.jboss.netty.handler.codec.http.HttpHeaders long getContentLength(org.jboss.netty.handler.codec.http.HttpMessage) 0'>
        <annotation name='org.jetbrains.annotations.NotNull'/>
    </item>
    <item name='org.jboss.netty.handler.codec.http.DefaultCookie int compareTo(java.lang.Object) 0'>
        <annotation name='org.jetbrains.annotations.NotNull'/>
    </item>
    <item name='org.jboss.netty.handler.codec.http.HttpMessage java.util.List&lt;java.util.Map.Entry&lt;java.lang.String,java.lang.String&gt;&gt; getHeaders()'>
        <annotation name='org.jetbrains.annotations.NotNull'/>
        <annotation name='org.jetbrains.kannotator.runtime.annotations.Propagated'>
            <val name="value" val="{org.jetbrains.kannotator.controlFlow.builder.analysis.NullabilityKey.class}"/>
        </annotation>
    </item>
    <item name='org.jboss.netty.handler.codec.http.HttpMessageDecoder org.jboss.netty.handler.codec.http.HttpMessage createMessage(java.lang.String[]) 0'>
        <annotation name='org.jetbrains.annotations.NotNull'/>
        <annotation name='org.jetbrains.kannotator.runtime.annotations.Propagated'>
            <val name="value" val="{org.jetbrains.kannotator.controlFlow.builder.analysis.NullabilityKey.class}"/>
        </annotation>
    </item>
    <item name='org.jboss.netty.handler.codec.http.HttpHeaders void addIntHeader(org.jboss.netty.handler.codec.http.HttpMessage, java.lang.String, int) 0'>
        <annotation name='org.jetbrains.annotations.NotNull'/>
    </item>
    <item name='org.jboss.netty.handler.codec.http.HttpMessage void removeHeader(java.lang.String) 0'>
        <annotation name='org.jetbrains.annotations.NotNull'/>
        <annotation name='org.jetbrains.kannotator.runtime.annotations.Propagated'>
            <val name="value" val="{org.jetbrains.kannotator.controlFlow.builder.analysis.NullabilityKey.class}"/>
        </annotation>
    </item>
    <item name='org.jboss.netty.handler.codec.http.Cookie void setPorts(java.lang.Iterable&lt;java.lang.Integer&gt;) 0'>
        <annotation name='org.jetbrains.annotations.NotNull'/>
        <annotation name='org.jetbrains.kannotator.runtime.annotations.Propagated'>
            <val name="value" val="{org.jetbrains.kannotator.controlFlow.builder.analysis.NullabilityKey.class}"/>
        </annotation>
    </item>
    <item name='org.jboss.netty.handler.codec.http.HttpChunkTrailer java.util.Set&lt;java.lang.String&gt; getHeaderNames()'>
        <annotation name='org.jetbrains.annotations.NotNull'/>
        <annotation name='org.jetbrains.kannotator.runtime.annotations.Propagated'>
            <val name="value" val="{org.jetbrains.kannotator.controlFlow.builder.analysis.NullabilityKey.class}"/>
        </annotation>
    </item>
    <item name='org.jboss.netty.handler.codec.http.QueryStringEncoder QueryStringEncoder(java.lang.String) 0'>
        <annotation name='org.jetbrains.annotations.NotNull'/>
    </item>
    <item name='org.jboss.netty.handler.codec.http.HttpHeaders int getIntHeader(org.jboss.netty.handler.codec.http.HttpMessage, java.lang.String, int) 0'>
        <annotation name='org.jetbrains.annotations.NotNull'/>
    </item>
    <item name='org.jboss.netty.handler.codec.http.HttpRequestDecoder org.jboss.netty.handler.codec.http.HttpMessage createMessage(java.lang.String[]) 0'>
        <annotation name='org.jetbrains.annotations.NotNull'/>
    </item>
    <item name='org.jboss.netty.handler.codec.http.DefaultHttpMessage java.util.Set&lt;java.lang.String&gt; getHeaderNames()'>
        <annotation name='org.jetbrains.annotations.NotNull'/>
    </item>
    <item name='org.jboss.netty.handler.codec.http.HttpResponseStatus int compareTo(java.lang.Object) 0'>
        <annotation name='org.jetbrains.annotations.NotNull'/>
    </item>
    <item name='org.jboss.netty.handler.codec.http.HttpChunkAggregator void messageReceived(org.jboss.netty.channel.ChannelHandlerContext, org.jboss.netty.channel.MessageEvent) 1'>
        <annotation name='org.jetbrains.annotations.NotNull'/>
    </item>
    <item name='org.jboss.netty.handler.codec.http.HttpMethod java.lang.String toString()'>
        <annotation name='org.jetbrains.annotations.NotNull'/>
    </item>
    <item name='org.jboss.netty.handler.codec.http.DefaultHttpResponse void setStatus(org.jboss.netty.handler.codec.http.HttpResponseStatus) 0'>
        <annotation name='org.jetbrains.annotations.NotNull'/>
    </item>
    <item name='org.jboss.netty.handler.codec.http.Cookie java.lang.String getName()'>
        <annotation name='org.jetbrains.annotations.NotNull'/>
        <annotation name='org.jetbrains.kannotator.runtime.annotations.Propagated'>
            <val name="value" val="{org.jetbrains.kannotator.controlFlow.builder.analysis.NullabilityKey.class}"/>
        </annotation>
    </item>
    <item name='org.jboss.netty.handler.codec.http.HttpMethod java.lang.String getName()'>
        <annotation name='org.jetbrains.annotations.NotNull'/>
    </item>
    <item name='org.jboss.netty.handler.codec.http.HttpChunkTrailer boolean containsHeader(java.lang.String) 0'>
        <annotation name='org.jetbrains.annotations.NotNull'/>
        <annotation name='org.jetbrains.kannotator.runtime.annotations.Propagated'>
            <val name="value" val="{org.jetbrains.kannotator.controlFlow.builder.analysis.NullabilityKey.class}"/>
        </annotation>
    </item>
    <item name='org.jboss.netty.handler.codec.http.HttpHeaders java.lang.String getHeader(org.jboss.netty.handler.codec.http.HttpMessage, java.lang.String) 0'>
        <annotation name='org.jetbrains.annotations.NotNull'/>
    </item>
    <item name='org.jboss.netty.handler.codec.http.HttpClientCodec void handleUpstream(org.jboss.netty.channel.ChannelHandlerContext, org.jboss.netty.channel.ChannelEvent) 0'>
        <annotation name='org.jetbrains.annotations.NotNull'/>
        <annotation name='org.jetbrains.kannotator.runtime.annotations.Propagated'>
            <val name="value" val="{org.jetbrains.kannotator.controlFlow.builder.analysis.NullabilityKey.class}"/>
        </annotation>
    </item>
    <item name='org.jboss.netty.handler.codec.http.HttpMessageDecoder org.jboss.netty.handler.codec.http.HttpMessage createMessage(java.lang.String[])'>
        <annotation name='org.jetbrains.annotations.NotNull'/>
        <annotation name='org.jetbrains.kannotator.runtime.annotations.Propagated'>
            <val name="value" val="{org.jetbrains.kannotator.controlFlow.builder.analysis.NullabilityKey.class}"/>
        </annotation>
    </item>
    <item name='org.jboss.netty.handler.codec.http.HttpHeaders void set100ContinueExpected(org.jboss.netty.handler.codec.http.HttpMessage, boolean) 0'>
        <annotation name='org.jetbrains.annotations.NotNull'/>
    </item>
    <item name='org.jboss.netty.handler.codec.http.HttpContentDecoder void beforeAdd(org.jboss.netty.channel.ChannelHandlerContext) 0'>
        <annotation name='org.jetbrains.annotations.NotNull'/>
        <annotation name='org.jetbrains.kannotator.runtime.annotations.Propagated'>
            <val name="value" val="{org.jetbrains.kannotator.controlFlow.builder.analysis.NullabilityKey.class}"/>
        </annotation>
    </item>
    <item name='org.jboss.netty.handler.codec.http.HttpMessage void setProtocolVersion(org.jboss.netty.handler.codec.http.HttpVersion) 0'>
        <annotation name='org.jetbrains.annotations.NotNull'/>
        <annotation name='org.jetbrains.kannotator.runtime.annotations.Propagated'>
            <val name="value" val="{org.jetbrains.kannotator.controlFlow.builder.analysis.NullabilityKey.class}"/>
        </annotation>
    </item>
</root>
